kelluwen/__init__.py
kelluwen/classes/__init__.py
kelluwen/classes/losses.py
kelluwen/classes/networks.py
kelluwen/functions/__init__.py
kelluwen/functions/data.py
kelluwen/functions/measures.py
kelluwen/functions/tools.py
kelluwen/functions/transforms.py
kelluwen-0.0.29.dist-info/LICENSE.txt
kelluwen-0.0.29.dist-info/METADATA
kelluwen-0.0.29.dist-info/WHEEL
kelluwen-0.0.29.dist-info/top_level.txt
kelluwen-0.0.29.dist-info/RECORD
