Metadata-Version: 2.1
Name: kelluwen
Version: 0.0.29
Summary: Open AI library for research and education.
Home-page: https://github.com/felipemoser/kelluwen
Author: Felipe Moser
Author-email: felipe.moser@univ.ox.ac.uk
Classifier: Development Status :: 3 - Alpha
Classifier: Operating System :: OS Independent
Classifier: Environment :: GPU :: NVIDIA CUDA
Classifier: Intended Audience :: Developers
Classifier: Intended Audience :: Education
Classifier: Intended Audience :: Science/Research
Classifier: Programming Language :: Python :: 3
Classifier: Programming Language :: Python :: 3.6
Classifier: Topic :: Education
Classifier: Topic :: Scientific/Engineering
Classifier: Topic :: Scientific/Engineering :: Artificial Intelligence
Classifier: Topic :: Scientific/Engineering :: Image Processing
Classifier: Topic :: Scientific/Engineering :: Medical Science Apps.
Requires-Dist: torch (>=1.10)
Requires-Dist: nibabel (>=3.2)
Requires-Dist: matplotlib (>=3.5)
Requires-Dist: typeguard (>=2.13.3)
